PyTrack/Experiment.py
PyTrack/Sensor.py
PyTrack/Stimulus.py
PyTrack/Subject.py
PyTrack/__init__.py
PyTrack/etDataReader.py
PyTrack/formatBridge.py
PyTrack_NTU-1.1.1.dist-info/LICENSE.txt
PyTrack_NTU-1.1.1.dist-info/METADATA
PyTrack_NTU-1.1.1.dist-info/WHEEL
PyTrack_NTU-1.1.1.dist-info/top_level.txt
PyTrack_NTU-1.1.1.dist-info/RECORD
