Metadata-Version: 2.1
Name: PyTrack-NTU
Version: 1.1.1
Summary: An end-to-end python analysis toolkit for eye tracking
Home-page: https://github.com/titoghose/PyTrack
Author: Upamanyu Ghose, Arvind Srinivasan
Author-email: titoghose@gmail.com, 96arvind@gmail.com
License: UNKNOWN
Platform: UNKNOWN
Classifier: Programming Language :: Python :: 3
Classifier: License :: OSI Approved :: GNU General Public License v3 (GPLv3)
Classifier: Operating System :: OS Independent
License-File: LICENSE.txt
Requires-Dist: numpy
Requires-Dist: scipy
Requires-Dist: matplotlib
Requires-Dist: pandas
Requires-Dist: Pillow (>=5.4.0)
Requires-Dist: sqlalchemy (>=1.2.15)
Requires-Dist: statsmodels
Requires-Dist: pingouin (==0.2.2)
